src/core/core_fetch.v
module core_fetch (
    input clk_i,
    input rst_i,

    // 来自EX/MEM阶段的分支信号
    input [31:0] pc_branch_i,// 分支目标地址
    input        pc_take_branch_i,// 是否发生分支

    // 来自流水线控制器的使能信号
    input        enable_i,// 允许取下一条指令

    // 与指令内存的接口（输入）
    input [31:0] mem_data_i,// 从内存读到的指令
    input        mem_done_i,// 内存操作完成

    // 输出到ID阶段
    output [31:0] pc_o,// 当前指令的PC
    output [31:0] inst_o,// 取到的指令

    // 与指令内存的接口（输出）
    output [31:0] mem_addr_o,// 要读取的地址
    output        mem_enable_o,// 内存使能信号

    // 流水线控制
    output        stall_o// 暂停信号（等待内存时）
);

  // 状态机定义
  localparam STATUS_IDLE = 2'b00;
  localparam STATUS_WAIT = 2'b01;

  reg [ 1:0] status_r;// 当前状态
  reg [31:0] pc_r;// 程序计数器
  reg [31:0] mem_data_r;// 保存从内存读到的指令
  reg        mem_enable_r;// 内存使能寄存器
  reg        stall_r;// 暂停信号寄存器

  assign pc_o         = pc_r;
  assign inst_o       = mem_data_r;
  assign mem_addr_o   = pc_r;
  assign mem_enable_o = mem_enable_r;
  assign stall_o      = stall_r;

  always @(posedge clk_i or posedge rst_i) begin
    if (rst_i) begin
      // 复位：回到IDLE状态，PC设为起始地址-8
      // 为什么是-8？因为第一次enable时会+4，实际从0x80000000开始
      status_r     <= STATUS_IDLE;
      pc_r         <= 32'h80000000 - 32'd8;
      mem_data_r   <= 32'b0;
      mem_enable_r <= 1'b0;
      stall_r      <= 1'b0;
    end else begin
      case (status_r)
      // IDLE状态：等待enable信号
        STATUS_IDLE: begin
          mem_enable_r <= 1'b0;
          stall_r      <= 1'b0;
          status_r     <= STATUS_IDLE;
          if (enable_i) begin
            // 收到enable：更新PC并发起内存请求
            pc_r         <= pc_take_branch_i ? pc_branch_i : pc_r + 4;
            mem_enable_r <= 1'b1;//发起内存读请求
            stall_r      <= 1'b1;//暂停流水线
            status_r     <= STATUS_WAIT;
          end
        end

        // WAIT状态：等待内存响应
        STATUS_WAIT: begin
          status_r     <= STATUS_WAIT;
          mem_enable_r <= 1'b0;//请求已发出，拉低使能
          if (mem_done_i) begin
            // 内存响应到达
            stall_r <= 1'b0;// 取消暂停
            mem_data_r <= mem_data_i;// 保存读到的指令
            status_r <= STATUS_IDLE;
          end
        end

        default: status_r <= STATUS_IDLE;
      endcase
    end
  end

endmodule

src/test/test_fetch.v
module test_fetch;
  reg         clk;
  reg         rst;

  reg  [31:0] pc_branch;
  reg         pc_take_branch;
  reg         enable;
  reg  [31:0] mem_data;
  reg         mem_done;
  reg  [31:0] mem_addr_r;

  wire [31:0] pc_o;
  wire [31:0] inst;
  wire [31:0] mem_addr;
  wire        mem_enable;
  wire        stall;

  core_fetch uut (
      .clk_i(clk),
      .rst_i(rst),
      .pc_branch_i(pc_branch),
      .pc_take_branch_i(pc_take_branch),
      .enable_i(enable),
      .mem_data_i(mem_data),
      .mem_done_i(mem_done),
      .pc_o(pc_o),
      .inst_o(inst),
      .mem_addr_o(mem_addr),
      .mem_enable_o(mem_enable),
      .stall_o(stall)
  );

  always #5 clk = ~clk;

  initial begin
    $dumpfile("test_fetch.vcd");
    $dumpvars(0, test_fetch);
    $display("----- FETCH testbench start -----");
    clk = 1'b0;
    rst = 1'b1;

    #10 rst = 1'b0;


    pc_branch = 32'h12345678;
    pc_take_branch = 1'b1;
    enable    = 1'b1;
    mem_done  = 1'b0;
    mem_data  = 32'h00000000;

    #10;
    pc_take_branch = 1'b0;
    enable = 1'b0;
    wait (mem_enable);
    mem_addr_r = mem_addr;
    #30;
    mem_done = 1'b1;
    mem_data = mem_addr_r;
    #10;
    mem_done = 1'b0;

    wait (!stall);
    enable = 1'b1;
    #10;
    enable = 1'b0;
    wait (mem_enable);
    mem_addr_r = mem_addr;
    #30;
    mem_done = 1'b1;
    mem_data = mem_addr_r;
    #10;
    mem_done = 1'b0;

    pc_branch = 32'h87654321;
    pc_take_branch = 1'b1;
    wait (!stall);
    enable = 1'b1;
    #10;
    enable = 1'b0;
    wait (mem_enable);
    mem_addr_r = mem_addr;
    #30;
    mem_done = 1'b1;
    mem_data = mem_addr_r;
    #10;
    mem_done = 1'b0;

    $display("----- FETCH testbench end -----");
    #100 $finish;
  end

endmodule

src/test/test_fetch.vcd
$date
	Wed Dec 24 01:30:39 2025
$end
$version
	Icarus Verilog
$end
$timescale
	1s
$end
$scope module test_fetch $end
$var wire 1 ! stall $end
$var wire 32 " pc_o [31:0] $end
$var wire 1 # mem_enable $end
$var wire 32 $ mem_addr [31:0] $end
$var wire 32 % inst [31:0] $end
$var reg 1 & clk $end
$var reg 1 ' enable $end
$var reg 32 ( mem_addr_r [31:0] $end
$var reg 32 ) mem_data [31:0] $end
$var reg 1 * mem_done $end
$var reg 32 + pc_branch [31:0] $end
$var reg 1 , pc_take_branch $end
$var reg 1 - rst $end
$scope module uut $end
$var wire 1 & clk_i $end
$var wire 1 ' enable_i $end
$var wire 32 . inst_o [31:0] $end
$var wire 32 / mem_addr_o [31:0] $end
$var wire 32 0 mem_data_i [31:0] $end
$var wire 1 * mem_done_i $end
$var wire 1 # mem_enable_o $end
$var wire 32 1 pc_branch_i [31:0] $end
$var wire 32 2 pc_o [31:0] $end
$var wire 1 , pc_take_branch_i $end
$var wire 1 - rst_i $end
$var wire 1 ! stall_o $end
$var parameter 2 3 STATUS_IDLE $end
$var parameter 2 4 STATUS_WAIT $end
$var reg 32 5 mem_data_r [31:0] $end
$var reg 1 6 mem_enable_r $end
$var reg 32 7 pc_r [31:0] $end
$var reg 1 8 stall_r $end
$var reg 2 9 status_r [1:0] $end
$upscope $end
$upscope $end
$enddefinitions $end
$comment Show the parameter values. $end
$dumpall
b1 4
b0 3
$end
#0
$dumpvars
b0 9
08
b1111111111111111111111111111000 7
06
b0 5
b1111111111111111111111111111000 2
bx 1
bx 0
b1111111111111111111111111111000 /
b0 .
1-
x,
bx +
x*
bx )
bx (
x'
0&
b0 %
b1111111111111111111111111111000 $
0#
b1111111111111111111111111111000 "
0!
$end
#5
1&
#10
0&
b0 )
b0 0
0*
1'
1,
b10010001101000101011001111000 +
b10010001101000101011001111000 1
0-
#15
b1 9
1!
18
1#
16
b10010001101000101011001111000 $
b10010001101000101011001111000 /
b10010001101000101011001111000 "
b10010001101000101011001111000 2
b10010001101000101011001111000 7
1&
#20
0&
b10010001101000101011001111000 (
0'
0,
#25
0#
06
1&
#30
0&
#35
1&
#40
0&
#45
1&
#50
0&
b10010001101000101011001111000 )
b10010001101000101011001111000 0
1*
#55
b0 9
b10010001101000101011001111000 %
b10010001101000101011001111000 .
b10010001101000101011001111000 5
0!
08
1&
#60
0&
1'
0*
#65
b1 9
1!
18
1#
16
b10010001101000101011001111100 $
b10010001101000101011001111100 /
b10010001101000101011001111100 "
b10010001101000101011001111100 2
b10010001101000101011001111100 7
1&
#70
0&
b10010001101000101011001111100 (
0'
#75
0#
06
1&
#80
0&
#85
1&
#90
0&
#95
1&
#100
0&
b10010001101000101011001111100 )
b10010001101000101011001111100 0
1*
#105
b0 9
b10010001101000101011001111100 %
b10010001101000101011001111100 .
b10010001101000101011001111100 5
0!
08
1&
#110
0&
1'
1,
b10000111011001010100001100100001 +
b10000111011001010100001100100001 1
0*
#115
b1 9
1!
18
1#
16
b10000111011001010100001100100001 $
b10000111011001010100001100100001 /
b10000111011001010100001100100001 "
b10000111011001010100001100100001 2
b10000111011001010100001100100001 7
1&
#120
0&
b10000111011001010100001100100001 (
0'
#125
0#
06
1&
#130
0&
#135
1&
#140
0&
#145
1&
#150
0&
b10000111011001010100001100100001 )
b10000111011001010100001100100001 0
1*
#155
b0 9
b10000111011001010100001100100001 %
b10000111011001010100001100100001 .
b10000111011001010100001100100001 5
0!
08
1&
#160
0&
0*
