src/core/core_defs.v
// ALU 操作码定义 (4位编码)
// 这些操作码用于控制ALU执行何种运算

`define ALU_NONE                  4'b0000  // 无操作
`define ALU_SHIFTL                4'b0001  // 逻辑左移 (<<)
`define ALU_SHIFTR                4'b0010  // 逻辑右移 (>>u)
`define ALU_SHIFTR_ARITH          4'b0011  // 算术右移 (>>s, 符号扩展)
`define ALU_ADD                   4'b0100  // 加法
`define ALU_SUB                   4'b0101  // 减法
`define ALU_AND                   4'b0110  // 按位与
`define ALU_OR                    4'b0111  // 按位或
`define ALU_XOR                   4'b1000  // 按位异或
`define ALU_LESS_THAN             4'b1001  // 无符号小于比较
`define ALU_LESS_THAN_SIGNED      4'b1010  // 有符号小于比较

// RV32I
// ----------------------------------------------------------------------------
// U-type 指令 (高位立即数)
// ----------------------------------------------------------------------------
// 格式: imm[31:12] | rd[11:7] | opcode[6:0]

// LUI - Load Upper Immediate
// 功能: x[rd] = imm << 12
// 用途: 加载高20位立即数到寄存器
`define INST_LUI                  32'b00000000000000000000000000110111
`define MASK_LUI                  32'b00000000000000000000000001111111


// AUIPC - Add Upper Immediate to PC
// 功能: x[rd] = pc + (imm << 12)
// 用途: PC相对寻址，常用于位置无关代码
`define INST_AUIPC                32'b00000000000000000000000000010111
`define MASK_AUIPC                32'b00000000000000000000000001111111

// ----------------------------------------------------------------------------
// J-type 指令 (无条件跳转)
// ----------------------------------------------------------------------------
// 格式: imm[20|10:1|11|19:12] | rd[11:7] | opcode[6:0]

// JAL - Jump and Link
// 功能: x[rd] = pc + 4; pc += imm
// 用途: 函数调用（rd=ra）或长跳转（rd=x0）
`define INST_JAL                  32'b00000000000000000000000001101111
`define MASK_JAL                  32'b00000000000000000000000001111111

// ----------------------------------------------------------------------------
// I-type 指令 (跳转)
// ----------------------------------------------------------------------------

// JALR - Jump and Link Register
// 功能: x[rd] = pc + 4; pc = (x[rs1] + imm) & ~1
// 用途: 间接跳转、函数返回（rs1=ra, rd=x0）
`define INST_JALR                 32'b00000000000000000000000001100111
`define MASK_JALR                 32'b00000000000000000111000001111111


// ----------------------------------------------------------------------------
// B-type 指令 (条件分支)
// ----------------------------------------------------------------------------
// 格式: imm[12|10:5] | rs2 | rs1 | funct3 | imm[4:1|11] | opcode
// 所有分支的跳转偏移是有符号数，以2字节为单位

// BEQ - Branch if Equal
// 功能: if (x[rs1] == x[rs2]) pc += imm
`define INST_BEQ                  32'b00000000000000000000000001100011
`define MASK_BEQ                  32'b00000000000000000111000001111111

// BNE - Branch if Not Equal
// 功能: if (x[rs1] != x[rs2]) pc += imm
`define INST_BNE                  32'b00000000000000000001000001100011
`define MASK_BNE                  32'b00000000000000000111000001111111

// BLT - Branch if Less Than (signed)
// 功能: if (x[rs1] <s x[rs2]) pc += imm
`define INST_BLT                  32'b00000000000000000100000001100011
`define MASK_BLT                  32'b00000000000000000111000001111111

// BGE - Branch if Greater or Equal (signed)
// 功能: if (x[rs1] ≥s x[rs2]) pc += imm
`define INST_BGE                  32'b00000000000000000101000001100011
`define MASK_BGE                  32'b00000000000000000111000001111111

// BLTU - Branch if Less Than (unsigned)
// 功能: if (x[rs1] <u x[rs2]) pc += imm
`define INST_BLTU                 32'b00000000000000000110000001100011
`define MASK_BLTU                 32'b00000000000000000111000001111111

// BGEU - Branch if Greater or Equal (unsigned)
// 功能: if (x[rs1] ≥u x[rs2]) pc += imm
`define INST_BGEU                 32'b00000000000000000111000001100011
`define MASK_BGEU                 32'b00000000000000000111000001111111


// ----------------------------------------------------------------------------
// I-type 指令 (加载 Load)
// ----------------------------------------------------------------------------
// 格式: imm[11:0] | rs1 | funct3 | rd | opcode
// 地址计算: addr = x[rs1] + sign_extend(imm)

// LB - Load Byte (sign-extended)
// 功能: x[rd] = sign_extend(M[addr][7:0])
`define INST_LB                   32'b00000000000000000000000000000011
`define MASK_LB                   32'b00000000000000000111000001111111

// LH - Load Halfword (sign-extended)
// 功能: x[rd] = sign_extend(M[addr][15:0])
`define INST_LH                   32'b00000000000000000001000000000011
`define MASK_LH                   32'b00000000000000000111000001111111

// LW - Load Word
// 功能: x[rd] = M[addr][31:0]
`define INST_LW                   32'b00000000000000000010000000000011
`define MASK_LW                   32'b00000000000000000111000001111111

// LBU - Load Byte Unsigned (zero-extended)
// 功能: x[rd] = zero_extend(M[addr][7:0])
`define INST_LBU                  32'b00000000000000000100000000000011
`define MASK_LBU                  32'b00000000000000000111000001111111

// LHU - Load Halfword Unsigned (zero-extended)
// 功能: x[rd] = zero_extend(M[addr][15:0])
`define INST_LHU                  32'b00000000000000000101000000000011
`define MASK_LHU                  32'b00000000000000000111000001111111

// ----------------------------------------------------------------------------
// S-type 指令 (存储 Store)
// ----------------------------------------------------------------------------
// 格式: imm[11:5] | rs2 | rs1 | funct3 | imm[4:0] | opcode
// 地址计算: addr = x[rs1] + sign_extend(imm)

// SB - Store Byte
// 功能: M[addr][7:0] = x[rs2][7:0]
`define INST_SB                   32'b00000000000000000000000000100011
`define MASK_SB                   32'b00000000000000000111000001111111

// SH - Store Halfword
// 功能: M[addr][15:0] = x[rs2][15:0]
`define INST_SH                   32'b00000000000000000001000000100011
`define MASK_SH                   32'b00000000000000000111000001111111

// SW - Store Word
// 功能: M[addr][31:0] = x[rs2][31:0]
`define INST_SW                   32'b00000000000000000010000000100011
`define MASK_SW                   32'b00000000000000000111000001111111


// ----------------------------------------------------------------------------
// I-type 指令 (立即数算术运算)
// ----------------------------------------------------------------------------

// ADDI - Add Immediate
// 功能: x[rd] = x[rs1] + sign_extend(imm)
// 注意: ADDI x0, x0, 0 是NOP指令
`define INST_ADDI                 32'b00000000000000000000000000010011
`define MASK_ADDI                 32'b00000000000000000111000001111111

// SLTI - Set Less Than Immediate (signed)
// 功能: x[rd] = (x[rs1] <s imm) ? 1 : 0
`define INST_SLTI                 32'b00000000000000000010000000010011
`define MASK_SLTI                 32'b00000000000000000111000001111111

// SLTIU - Set Less Than Immediate Unsigned
// 功能: x[rd] = (x[rs1] <u imm) ? 1 : 0
// 注意: 用于判断x[rs1]是否为0 (SLTIU rd, rs1, 1)
`define INST_SLTIU                32'b00000000000000000011000000010011
`define MASK_SLTIU                32'b00000000000000000111000001111111

// XORI - XOR Immediate
// 功能: x[rd] = x[rs1] ^ sign_extend(imm)
// 注意: XORI rd, rs1, -1 是NOT指令
`define INST_XORI                 32'b00000000000000000100000000010011
`define MASK_XORI                 32'b00000000000000000111000001111111

// ORI - OR Immediate
// 功能: x[rd] = x[rs1] | sign_extend(imm)
`define INST_ORI                  32'b00000000000000000110000000010011
`define MASK_ORI                  32'b00000000000000000111000001111111

// ANDI - AND Immediate
// 功能: x[rd] = x[rs1] & sign_extend(imm)
`define INST_ANDI                 32'b00000000000000000111000000010011
`define MASK_ANDI                 32'b00000000000000000111000001111111


// ----------------------------------------------------------------------------
// I-type 指令 (移位操作，特殊编码)
// ----------------------------------------------------------------------------
// 格式: funct7 | shamt[4:0] | rs1 | funct3 | rd | opcode
// shamt: 移位量，0-31

// SLLI - Shift Left Logical Immediate
// 功能: x[rd] = x[rs1] << shamt
`define INST_SLLI                 32'b00000000000000000001000000010011
`define MASK_SLLI                 32'b11111110000000000111000001111111

// SRLI - Shift Right Logical Immediate
// 功能: x[rd] = x[rs1] >>u shamt (逻辑右移，高位补0)
`define INST_SRLI                 32'b00000000000000000101000000010011
`define MASK_SRLI                 32'b11111110000000000111000001111111

// SRAI - Shift Right Arithmetic Immediate
// 功能: x[rd] = x[rs1] >>s shamt (算术右移，符号扩展)
`define INST_SRAI                 32'b01000000000000000101000000010011
`define MASK_SRAI                 32'b11111110000000000111000001111111


// ----------------------------------------------------------------------------
// R-type 指令 (寄存器间运算)
// ----------------------------------------------------------------------------
// 格式: funct7 | rs2 | rs1 | funct3 | rd | opcode

// ADD - Add
// 功能: x[rd] = x[rs1] + x[rs2]
`define INST_ADD                  32'b00000000000000000000000000110011
`define MASK_ADD                  32'b11111110000000000111000001111111

// SUB - Subtract
// 功能: x[rd] = x[rs1] - x[rs2]
`define INST_SUB                  32'b01000000000000000000000000110011
`define MASK_SUB                  32'b11111110000000000111000001111111

// SLL - Shift Left Logical
// 功能: x[rd] = x[rs1] << x[rs2][4:0]
`define INST_SLL                  32'b00000000000000000001000000110011
`define MASK_SLL                  32'b11111110000000000111000001111111

// SLT - Set Less Than (signed)
// 功能: x[rd] = (x[rs1] <s x[rs2]) ? 1 : 0
`define INST_SLT                  32'b00000000000000000010000000110011
`define MASK_SLT                  32'b11111110000000000111000001111111

// SLTU - Set Less Than Unsigned
// 功能: x[rd] = (x[rs1] <u x[rs2]) ? 1 : 0
`define INST_SLTU                 32'b00000000000000000011000000110011
`define MASK_SLTU                 32'b11111110000000000111000001111111

// XOR - XOR
// 功能: x[rd] = x[rs1] ^ x[rs2]
`define INST_XOR                  32'b00000000000000000100000000110011
`define MASK_XOR                  32'b11111110000000000111000001111111

// SRL - Shift Right Logical
// 功能: x[rd] = x[rs1] >>u x[rs2][4:0]
`define INST_SRL                  32'b00000000000000000101000000110011
`define MASK_SRL                  32'b11111110000000000111000001111111

// SRA - Shift Right Arithmetic
// 功能: x[rd] = x[rs1] >>s x[rs2][4:0]
`define INST_SRA                  32'b01000000000000000101000000110011
`define MASK_SRA                  32'b11111110000000000111000001111111

// OR - OR
// 功能: x[rd] = x[rs1] | x[rs2]
`define INST_OR                   32'b00000000000000000110000000110011
`define MASK_OR                   32'b11111110000000000111000001111111

// AND - AND
// 功能: x[rd] = x[rs1] & x[rs2]
`define INST_AND                  32'b00000000000000000111000000110011
`define MASK_AND                  32'b11111110000000000111000001111111


// ----------------------------------------------------------------------------
// 内存屏障和同步指令
// ----------------------------------------------------------------------------

// FENCE - Fence Memory and I/O
// 功能: 保证内存访问顺序
`define INST_FENCE                32'b00000000000000000000000000001111
`define MASK_FENCE                32'b00000000000000000111000001111111

// PAUSE - Pause Hint
// 功能: 提示处理器可以降低功耗（在自旋锁中使用）
`define INST_PAUSE                32'b00000001000000000000000000001111
`define MASK_PAUSE                32'b11111111111111111111111111111111

// ============================================================================
// RV32M 乘除法扩展
// ============================================================================
// 所有乘除法指令都是R-type格式
// funct7=0000001 标识M扩展指令

// MUL - Multiply (取低32位)
// 功能: x[rd] = (x[rs1] * x[rs2])[31:0]
`define INST_MUL                  32'b00000010000000000000000000110011
`define MASK_MUL                  32'b11111110000000000111000001111111

// MULH - Multiply High (signed × signed，取高32位)
// 功能: x[rd] = (x[rs1] *s x[rs2])[63:32]
`define INST_MULH                 32'b00000010000000000001000000110011
`define MASK_MULH                 32'b11111110000000000111000001111111

// MULHSU - Multiply High (signed × unsigned，取高32位)
// 功能: x[rd] = (x[rs1]_signed * x[rs2]_unsigned)[63:32]
`define INST_MULHSU               32'b00000010000000000010000000110011
`define MASK_MULHSU               32'b11111110000000000111000001111111

// MULHU - Multiply High (unsigned × unsigned，取高32位)
// 功能: x[rd] = (x[rs1] *u x[rs2])[63:32]
`define INST_MULHU                32'b00000010000000000011000000110011
`define MASK_MULHU                32'b11111110000000000111000001111111

// DIV - Divide (signed)
// 功能: x[rd] = x[rs1] ÷s x[rs2]
// 注意: 除0结果为-1，溢出(最小值÷-1)结果为最小值
`define INST_DIV                  32'b00000010000000000100000000110011
`define MASK_DIV                  32'b11111110000000000111000001111111

// DIVU - Divide (unsigned)
// 功能: x[rd] = x[rs1] ÷u x[rs2]
// 注意: 除0结果为2^32-1
`define INST_DIVU                 32'b00000010000000000101000000110011
`define MASK_DIVU                 32'b11111110000000000111000001111111

// REM - Remainder (signed)
// 功能: x[rd] = x[rs1] %s x[rs2]
// 注意: 除0结果为被除数，溢出结果为0
`define INST_REM                  32'b00000010000000000110000000110011
`define MASK_REM                  32'b11111110000000000111000001111111

// REMU - Remainder (unsigned)
// 功能: x[rd] = x[rs1] %u x[rs2]
// 注意: 除0结果为被除数
`define INST_REMU                 32'b00000010000000000111000000110011
`define MASK_REMU                 32'b11111110000000000111000001111111

// ============================================================================
// RV32Zicsr 控制状态寄存器扩展
// ============================================================================
// CSR指令格式: csr[31:20] | rs1/uimm[19:15] | funct3[14:12] | rd[11:7] | opcode

// CSRRW - CSR Read and Write
// 功能: t=CSR[csr]; CSR[csr]=x[rs1]; x[rd]=t
`define INST_CSRRW                32'b00000000000000000001000001110011
`define MASK_CSRRW                32'b00000000000000000111000001111111

// CSRRS - CSR Read and Set
// 功能: t=CSR[csr]; CSR[csr]=t|x[rs1]; x[rd]=t
`define INST_CSRRS                32'b00000000000000000010000001110011
`define MASK_CSRRS                32'b00000000000000000111000001111111

// CSRRC - CSR Read and Clear
// 功能: t=CSR[csr]; CSR[csr]=t&~x[rs1]; x[rd]=t
`define INST_CSRRC                32'b00000000000000000011000001110011
`define MASK_CSRRC                32'b00000000000000000111000001111111

// CSRRWI - CSR Read and Write Immediate
// 功能: x[rd]=CSR[csr]; CSR[csr]=zero_extend(uimm)
`define INST_CSRRWI               32'b00000000000000000101000001110011
`define MASK_CSRRWI               32'b00000000000000000111000001111111

// CSRRSI - CSR Read and Set Immediate
// 功能: t=CSR[csr]; CSR[csr]=t|zero_extend(uimm); x[rd]=t
`define INST_CSRRSI               32'b00000000000000000110000001110011
`define MASK_CSRRSI               32'b00000000000000000111000001111111

// CSRRCI - CSR Read and Clear Immediate
// 功能: t=CSR[csr]; CSR[csr]=t&~zero_extend(uimm); x[rd]=t
`define INST_CSRRCI               32'b00000000000000000111000001110011
`define MASK_CSRRCI               32'b00000000000000000111000001111111

// ============================================================================
// RV32 特权指令
// ============================================================================

// ECALL - Environment Call
// 功能: 触发环境调用异常
// 用途: 系统调用（从U模式到S模式，或从S模式到M模式）
`define INST_ECALL                32'b00000000000000000000000001110011
`define MASK_ECALL                32'b11111111111111111111111111111111

// EBREAK - Environment Break
// 功能: 触发断点异常
// 用途: 调试器设置断点
`define INST_EBREAK               32'b00000000000100000000000001110011
`define MASK_EBREAK               32'b11111111111111111111111111111111

// MRET - Machine-mode Return
// 功能: 从机器模式陷阱返回
// 操作: pc=mepc; 恢复mstatus中的中断使能位
`define INST_MRET                 32'b00110000001000000000000001110011
`define MASK_MRET                 32'b11111111111111111111111111111111

// ============================================================================
// CSR 寄存器地址定义
// ============================================================================
// CSR地址为12位，[11:10]表示特权级别
`define CSR_MHARTID               32'hf14  // Hardware thread ID (只读)

// Machine Trap Setup
`define CSR_MSTATUS               32'h300  // Machine status register
`define CSR_MISA                  32'h301  // ISA and extensions (只读)
`define CSR_MIE                   32'h304  // Machine interrupt-enable register
`define CSR_MTVEC                 32'h305  // Machine trap-handler base address

// Machine Trap Handling
`define CSR_MSCRATCH              32'h340  // Scratch register for trap handlers
`define CSR_MEPC                  32'h341  // Machine exception program counter
`define CSR_MCAUSE                32'h342  // Machine trap cause
`define CSR_MTVAL                 32'h343  // Machine bad address or instruction
`define CSR_MIP                   32'h344  // Machine interrupt pending

// Machine Counter/Timers
`define CSR_MCYCLE                32'hb00  // Machine cycle counter
`define CSR_MINSTRET              32'hb02  // Machine instructions-retired counter

src/core/core_alu.v
`include "core_defs.v"

module core_alu (
  input  [3:0]  alu_op_i,      // 4位操作码，支持16种操作（当前用11种）
  input  [31:0] alu_a_i,       // 32位操作数A（可能是寄存器值、PC、立即数等）
  input  [31:0] alu_b_i,       // 32位操作数B（可能是寄存器值、立即数等）

  output [31:0] alu_r_o        // 32位运算结果
);


  // 减法结果（预先计算，供减法操作使用）
  wire [31:0] alu_sub_r = alu_a_i - alu_b_i;

  // 最终结果寄存器
  reg  [31:0] result_r;
  assign alu_r_o = result_r;

  // 移位量（只使用低5位，因为32位数最多移31位）
  wire [4:0] shift_amount = alu_b_i[4:0];

  always @(alu_op_i or alu_a_i or alu_b_i or alu_sub_r or shift_amount) begin
    result_r = 32'h0;

    case (alu_op_i)

      // 逻辑左移 - 使用Verilog移位运算符
      `ALU_SHIFTL: begin
        result_r = alu_a_i << shift_amount;
      end

      // 逻辑右移 - 使用Verilog移位运算符
      `ALU_SHIFTR: begin
        result_r = alu_a_i >> shift_amount;
      end

      // 算术右移 - 使用Verilog有符号移位运算符
      `ALU_SHIFTR_ARITH: begin
        result_r = $signed(alu_a_i) >>> shift_amount;
      end

      `ALU_ADD: result_r = alu_a_i + alu_b_i;

      `ALU_SUB: result_r = alu_sub_r;

      `ALU_AND: result_r = alu_a_i & alu_b_i;

      `ALU_OR: result_r = alu_a_i | alu_b_i;

      `ALU_XOR: result_r = alu_a_i ^ alu_b_i;

      `ALU_LESS_THAN: begin
        result_r = (alu_a_i < alu_b_i) ? 32'h1 : 32'h0;
      end

      `ALU_LESS_THAN_SIGNED: begin
        result_r = ($signed(alu_a_i) < $signed(alu_b_i)) ? 32'h1 : 32'h0;
      end

      default: result_r = alu_a_i;
    endcase
  end
endmodule

src/test/test_alu.v
`timescale 1ns / 1ps
`include "../core/core_defs.v"

module test_alu ();
  reg  [ 3:0] opcode;
  reg  [31:0] a;
  reg  [31:0] b;
  wire [31:0] r;

  // 实例化ALU
  core_alu alu (
      .alu_op_i(opcode),
      .alu_a_i (a),
      .alu_b_i (b),
      .alu_r_o (r)
  );
  
  integer i;

  initial begin
    $dumpfile("test_alu.vcd");      // 生成波形文件
    $dumpvars(0, test_alu);
    
    // 测试1：逻辑左移 - 遍历所有移位量（0-31位）
    $display("----- SHIFTL test start -----");
    opcode = `ALU_SHIFTL;
    a = 32'hffffffff;              // 全1，方便观察移位效果
    b = 32'b0;
    
    for (i = 0; i < 32; i = i + 1) begin
      b = b + 1'b1;
      #5;                          // 在显示前等待组合逻辑稳定
      $display("a = %b, b = %b, result = %b", a, b, r);
    end
    
    // 测试2：逻辑右移 - 遍历所有移位量
    $display("----- SHIFTR test start -----");
    opcode = `ALU_SHIFTR;
    a = 32'hffffffff;
    b = 32'b0;
    
    for (i = 0; i < 32; i = i + 1) begin
      b = b + 1'b1;
      #5;                          // 在显示前等待组合逻辑稳定
      $display("a = %b, b = %b, result = %b", a, b, r);
    end
    
    // 测试3：算术右移（负数） - 验证符号扩展
    $display("----- SHIFTR_ARITH negative test start -----");
    opcode = `ALU_SHIFTR_ARITH;
    a = 32'h80000000;              // 最小负数
    b = 32'b0;
    
    for (i = 0; i < 32; i = i + 1) begin
      b = b + 1'b1;
      #5;                          // 在显示前等待组合逻辑稳定
      $display("a = %b, b = %b, result = %b", a, b, r);
    end
    
    // 测试4：算术右移（正数） - 验证零扩展
    $display("----- SHIFTR_ARITH positive test start -----");
    a = 32'h7fffffff;              // 最大正数
    b = 32'b0;
    
    for (i = 0; i < 32; i = i + 1) begin
      b = b + 1'b1;
      #5;                          // 在显示前等待组合逻辑稳定
      $display("a = %b, b = %b, result = %b", a, b, r);
    end
    
    // =================================================================
    // 测试5-10：其他运算
    // =================================================================
    
    // 加法测试
    opcode = `ALU_ADD;
    a = 32'h12345678;
    b = 32'h01234567;
    #5;
    $display("ADD: %h + %h = %h", a, b, r);
    
    // 减法测试
    opcode = `ALU_SUB;
    #5;
    $display("SUB: %h - %h = %h", a, b, r);
    
    // 按位与测试
    opcode = `ALU_AND;
    #5;
    $display("AND: %h & %h = %h", a, b, r);
    
    // 按位或测试
    opcode = `ALU_OR;
    #5;
    $display("OR: %h | %h = %h", a, b, r);
    
    // 按位异或测试
    opcode = `ALU_XOR;
    #5;
    $display("XOR: %h ^ %h = %h", a, b, r);
    
    // 无符号比较测试
    opcode = `ALU_LESS_THAN;
    #5;
    $display("SLTU: %h < %h = %d", a, b, r);
    
    // 有符号比较测试
    opcode = `ALU_LESS_THAN_SIGNED;
    a = 32'h12345678;              // 正数
    b = 32'hf1234567;              // 负数
    #5;
    $display("SLT: %h < %h = %d", a, b, r);
  end
endmodule

src/test/test_alu.vcd
$date
	Mon Dec 22 22:50:22 2025
$end
$version
	Icarus Verilog
$end
$timescale
	1ps
$end
$scope module test_alu $end
$var wire 32 ! r [31:0] $end
$var reg 32 " a [31:0] $end
$var reg 32 # b [31:0] $end
$var reg 4 $ opcode [3:0] $end
$var integer 32 % i [31:0] $end
$scope module alu $end
$var wire 32 & alu_a_i [31:0] $end
$var wire 32 ' alu_b_i [31:0] $end
$var wire 4 ( alu_op_i [3:0] $end
$var wire 32 ) alu_r_o [31:0] $end
$var wire 5 * shift_amount [4:0] $end
$var wire 32 + alu_sub_r [31:0] $end
$var reg 32 , result_r [31:0] $end
$upscope $end
$upscope $end
$enddefinitions $end
$comment Show the parameter values. $end
$dumpall
$end
#0
$dumpvars
b11111111111111111111111111111110 ,
b11111111111111111111111111111110 +
b1 *
b11111111111111111111111111111110 )
b1 (
b1 '
b11111111111111111111111111111111 &
b0 %
b1 $
b1 #
b11111111111111111111111111111111 "
b11111111111111111111111111111110 !
$end
#5000
b11111111111111111111111111111100 !
b11111111111111111111111111111100 )
b11111111111111111111111111111100 ,
b10 *
b11111111111111111111111111111101 +
b10 #
b10 '
b1 %
#10000
b11111111111111111111111111111000 !
b11111111111111111111111111111000 )
b11111111111111111111111111111000 ,
b11 *
b11111111111111111111111111111100 +
b11 #
b11 '
b10 %
#15000
b11111111111111111111111111110000 !
b11111111111111111111111111110000 )
b11111111111111111111111111110000 ,
b100 *
b11111111111111111111111111111011 +
b100 #
b100 '
b11 %
#20000
b11111111111111111111111111100000 !
b11111111111111111111111111100000 )
b11111111111111111111111111100000 ,
b101 *
b11111111111111111111111111111010 +
b101 #
b101 '
b100 %
#25000
b11111111111111111111111111000000 !
b11111111111111111111111111000000 )
b11111111111111111111111111000000 ,
b110 *
b11111111111111111111111111111001 +
b110 #
b110 '
b101 %
#30000
b11111111111111111111111110000000 !
b11111111111111111111111110000000 )
b11111111111111111111111110000000 ,
b111 *
b11111111111111111111111111111000 +
b111 #
b111 '
b110 %
#35000
b11111111111111111111111100000000 !
b11111111111111111111111100000000 )
b11111111111111111111111100000000 ,
b1000 *
b11111111111111111111111111110111 +
b1000 #
b1000 '
b111 %
#40000
b11111111111111111111111000000000 !
b11111111111111111111111000000000 )
b11111111111111111111111000000000 ,
b1001 *
b11111111111111111111111111110110 +
b1001 #
b1001 '
b1000 %
#45000
b11111111111111111111110000000000 !
b11111111111111111111110000000000 )
b11111111111111111111110000000000 ,
b1010 *
b11111111111111111111111111110101 +
b1010 #
b1010 '
b1001 %
#50000
b11111111111111111111100000000000 !
b11111111111111111111100000000000 )
b11111111111111111111100000000000 ,
b1011 *
b11111111111111111111111111110100 +
b1011 #
b1011 '
b1010 %
#55000
b11111111111111111111000000000000 !
b11111111111111111111000000000000 )
b11111111111111111111000000000000 ,
b1100 *
b11111111111111111111111111110011 +
b1100 #
b1100 '
b1011 %
#60000
b11111111111111111110000000000000 !
b11111111111111111110000000000000 )
b11111111111111111110000000000000 ,
b1101 *
b11111111111111111111111111110010 +
b1101 #
b1101 '
b1100 %
#65000
b11111111111111111100000000000000 !
b11111111111111111100000000000000 )
b11111111111111111100000000000000 ,
b1110 *
b11111111111111111111111111110001 +
b1110 #
b1110 '
b1101 %
#70000
b11111111111111111000000000000000 !
b11111111111111111000000000000000 )
b11111111111111111000000000000000 ,
b1111 *
b11111111111111111111111111110000 +
b1111 #
b1111 '
b1110 %
#75000
b11111111111111110000000000000000 !
b11111111111111110000000000000000 )
b11111111111111110000000000000000 ,
b10000 *
b11111111111111111111111111101111 +
b10000 #
b10000 '
b1111 %
#80000
b11111111111111100000000000000000 !
b11111111111111100000000000000000 )
b11111111111111100000000000000000 ,
b10001 *
b11111111111111111111111111101110 +
b10001 #
b10001 '
b10000 %
#85000
b11111111111111000000000000000000 !
b11111111111111000000000000000000 )
b11111111111111000000000000000000 ,
b10010 *
b11111111111111111111111111101101 +
b10010 #
b10010 '
b10001 %
#90000
b11111111111110000000000000000000 !
b11111111111110000000000000000000 )
b11111111111110000000000000000000 ,
b10011 *
b11111111111111111111111111101100 +
b10011 #
b10011 '
b10010 %
#95000
b11111111111100000000000000000000 !
b11111111111100000000000000000000 )
b11111111111100000000000000000000 ,
b10100 *
b11111111111111111111111111101011 +
b10100 #
b10100 '
b10011 %
#100000
b11111111111000000000000000000000 !
b11111111111000000000000000000000 )
b11111111111000000000000000000000 ,
b10101 *
b11111111111111111111111111101010 +
b10101 #
b10101 '
b10100 %
#105000
b11111111110000000000000000000000 !
b11111111110000000000000000000000 )
b11111111110000000000000000000000 ,
b10110 *
b11111111111111111111111111101001 +
b10110 #
b10110 '
b10101 %
#110000
b11111111100000000000000000000000 !
b11111111100000000000000000000000 )
b11111111100000000000000000000000 ,
b10111 *
b11111111111111111111111111101000 +
b10111 #
b10111 '
b10110 %
#115000
b11111111000000000000000000000000 !
b11111111000000000000000000000000 )
b11111111000000000000000000000000 ,
b11000 *
b11111111111111111111111111100111 +
b11000 #
b11000 '
b10111 %
#120000
b11111110000000000000000000000000 !
b11111110000000000000000000000000 )
b11111110000000000000000000000000 ,
b11001 *
b11111111111111111111111111100110 +
b11001 #
b11001 '
b11000 %
#125000
b11111100000000000000000000000000 !
b11111100000000000000000000000000 )
b11111100000000000000000000000000 ,
b11010 *
b11111111111111111111111111100101 +
b11010 #
b11010 '
b11001 %
#130000
b11111000000000000000000000000000 !
b11111000000000000000000000000000 )
b11111000000000000000000000000000 ,
b11011 *
b11111111111111111111111111100100 +
b11011 #
b11011 '
b11010 %
#135000
b11110000000000000000000000000000 !
b11110000000000000000000000000000 )
b11110000000000000000000000000000 ,
b11100 *
b11111111111111111111111111100011 +
b11100 #
b11100 '
b11011 %
#140000
b11100000000000000000000000000000 !
b11100000000000000000000000000000 )
b11100000000000000000000000000000 ,
b11101 *
b11111111111111111111111111100010 +
b11101 #
b11101 '
b11100 %
#145000
b11000000000000000000000000000000 !
b11000000000000000000000000000000 )
b11000000000000000000000000000000 ,
b11110 *
b11111111111111111111111111100001 +
b11110 #
b11110 '
b11101 %
#150000
b10000000000000000000000000000000 !
b10000000000000000000000000000000 )
b10000000000000000000000000000000 ,
b11111 *
b11111111111111111111111111100000 +
b11111 #
b11111 '
b11110 %
#155000
b11111111111111111111111111111111 !
b11111111111111111111111111111111 )
b11111111111111111111111111111111 ,
b0 *
b11111111111111111111111111011111 +
b100000 #
b100000 '
b11111 %
#160000
b1 *
b1111111111111111111111111111111 !
b1111111111111111111111111111111 )
b1111111111111111111111111111111 ,
b11111111111111111111111111111110 +
b1 #
b1 '
b10 $
b10 (
b0 %
#165000
b111111111111111111111111111111 !
b111111111111111111111111111111 )
b111111111111111111111111111111 ,
b10 *
b11111111111111111111111111111101 +
b10 #
b10 '
b1 %
#170000
b11111111111111111111111111111 !
b11111111111111111111111111111 )
b11111111111111111111111111111 ,
b11 *
b11111111111111111111111111111100 +
b11 #
b11 '
b10 %
#175000
b1111111111111111111111111111 !
b1111111111111111111111111111 )
b1111111111111111111111111111 ,
b100 *
b11111111111111111111111111111011 +
b100 #
b100 '
b11 %
#180000
b111111111111111111111111111 !
b111111111111111111111111111 )
b111111111111111111111111111 ,
b101 *
b11111111111111111111111111111010 +
b101 #
b101 '
b100 %
#185000
b11111111111111111111111111 !
b11111111111111111111111111 )
b11111111111111111111111111 ,
b110 *
b11111111111111111111111111111001 +
b110 #
b110 '
b101 %
#190000
b1111111111111111111111111 !
b1111111111111111111111111 )
b1111111111111111111111111 ,
b111 *
b11111111111111111111111111111000 +
b111 #
b111 '
b110 %
#195000
b111111111111111111111111 !
b111111111111111111111111 )
b111111111111111111111111 ,
b1000 *
b11111111111111111111111111110111 +
b1000 #
b1000 '
b111 %
#200000
b11111111111111111111111 !
b11111111111111111111111 )
b11111111111111111111111 ,
b1001 *
b11111111111111111111111111110110 +
b1001 #
b1001 '
b1000 %
#205000
b1111111111111111111111 !
b1111111111111111111111 )
b1111111111111111111111 ,
b1010 *
b11111111111111111111111111110101 +
b1010 #
b1010 '
b1001 %
#210000
b111111111111111111111 !
b111111111111111111111 )
b111111111111111111111 ,
b1011 *
b11111111111111111111111111110100 +
b1011 #
b1011 '
b1010 %
#215000
b11111111111111111111 !
b11111111111111111111 )
b11111111111111111111 ,
b1100 *
b11111111111111111111111111110011 +
b1100 #
b1100 '
b1011 %
#220000
b1111111111111111111 !
b1111111111111111111 )
b1111111111111111111 ,
b1101 *
b11111111111111111111111111110010 +
b1101 #
b1101 '
b1100 %
#225000
b111111111111111111 !
b111111111111111111 )
b111111111111111111 ,
b1110 *
b11111111111111111111111111110001 +
b1110 #
b1110 '
b1101 %
#230000
b11111111111111111 !
b11111111111111111 )
b11111111111111111 ,
b1111 *
b11111111111111111111111111110000 +
b1111 #
b1111 '
b1110 %
#235000
b1111111111111111 !
b1111111111111111 )
b1111111111111111 ,
b10000 *
b11111111111111111111111111101111 +
b10000 #
b10000 '
b1111 %
#240000
b111111111111111 !
b111111111111111 )
b111111111111111 ,
b10001 *
b11111111111111111111111111101110 +
b10001 #
b10001 '
b10000 %
#245000
b11111111111111 !
b11111111111111 )
b11111111111111 ,
b10010 *
b11111111111111111111111111101101 +
b10010 #
b10010 '
b10001 %
#250000
b1111111111111 !
b1111111111111 )
b1111111111111 ,
b10011 *
b11111111111111111111111111101100 +
b10011 #
b10011 '
b10010 %
#255000
b111111111111 !
b111111111111 )
b111111111111 ,
b10100 *
b11111111111111111111111111101011 +
b10100 #
b10100 '
b10011 %
#260000
b11111111111 !
b11111111111 )
b11111111111 ,
b10101 *
b11111111111111111111111111101010 +
b10101 #
b10101 '
b10100 %
#265000
b1111111111 !
b1111111111 )
b1111111111 ,
b10110 *
b11111111111111111111111111101001 +
b10110 #
b10110 '
b10101 %
#270000
b111111111 !
b111111111 )
b111111111 ,
b10111 *
b11111111111111111111111111101000 +
b10111 #
b10111 '
b10110 %
#275000
b11111111 !
b11111111 )
b11111111 ,
b11000 *
b11111111111111111111111111100111 +
b11000 #
b11000 '
b10111 %
